LICENSE
MANIFEST.in
README.md
setup.cfg
setup.py
rse/__init__.py
rse/defaults.py
rse/exceptions.py
rse/version.py
rse.egg-info/PKG-INFO
rse.egg-info/SOURCES.txt
rse.egg-info/dependency_links.txt
rse.egg-info/entry_points.txt
rse.egg-info/not-zip-safe
rse.egg-info/requires.txt
rse.egg-info/top_level.txt
rse/app/__init__.py
rse/app/api.py
rse/app/config.py
rse/app/export.py
rse/app/server.py
rse/app/static/css/style.css
rse/app/static/css/topics.css
rse/app/templates/base.html
rse/app/templates/search.html
rse/app/templates/annotate/criteria-static.html
rse/app/templates/annotate/criteria.html
rse/app/templates/annotate/repos.html
rse/app/templates/annotate/taxonomy-static.html
rse/app/templates/annotate/taxonomy.html
rse/app/templates/home/filesystem-index.html
rse/app/templates/home/index.html
rse/app/templates/main/criteria.html
rse/app/templates/main/taxonomy.html
rse/app/templates/parsers/github.html
rse/app/templates/parsers/gitlab.html
rse/app/templates/tables/criteria-answer-table.html
rse/app/templates/tables/criteria-table.html
rse/app/templates/tables/taxonomy-table.html
rse/app/templates/topics/base.html
rse/app/templates/topics/index.html
rse/app/views/__init__.py
rse/app/views/main.py
rse/app/views/repositories.py
rse/client/__init__.py
rse/client/add.py
rse/client/annotate.py
rse/client/clear.py
rse/client/config.py
rse/client/exists.py
rse/client/export.py
rse/client/generate.py
rse/client/get.py
rse/client/imp.py
rse/client/init.py
rse/client/label.py
rse/client/listing.py
rse/client/metrics.py
rse/client/scrape.py
rse/client/search.py
rse/client/shell.py
rse/client/start.py
rse/client/topics.py
rse/client/update.py
rse/logger/__init__.py
rse/logger/message.py
rse/main/__init__.py
rse/main/criteria.py
rse/main/taxonomy.py
rse/main/config/__init__.py
rse/main/config/config.ini
rse/main/database/__init__.py
rse/main/database/base.py
rse/main/database/filesystem.py
rse/main/database/models.py
rse/main/database/relational.py
rse/main/database/sqlite.py
rse/main/export/__init__.py
rse/main/export/jekyll/.gitignore
rse/main/export/jekyll/Gemfile
rse/main/export/jekyll/LICENSE
rse/main/export/jekyll/README.md
rse/main/export/jekyll/_config.yml
