Metadata-Version: 2.1
Name: rse
Version: 0.0.48
Summary: tools for assessment and categorization of research software
Home-page: https://github.com/rseng/rse
Author: Vanessa Sochat
Author-email: vsoch@users.noreply.github.io
Maintainer: Vanessa Sochat
Maintainer-email: vsoch@users.noreply.github.io
License: LICENSE
Keywords: rse,software,research software,database,taxonomy
Classifier: Intended Audience :: Science/Research
Classifier: Intended Audience :: Developers
Classifier: License :: OSI Approved :: Mozilla Public License 2.0 (MPL 2.0)
Classifier: Topic :: Software Development
Classifier: Topic :: Scientific/Engineering
Classifier: Natural Language :: English
Classifier: Operating System :: Unix
Classifier: Programming Language :: Python :: 3
Classifier: Programming Language :: Python :: 3.5
Classifier: Programming Language :: Python :: 3.6
Classifier: Programming Language :: Python :: 3.7
Classifier: Programming Language :: Python :: 3.8
Provides-Extra: database
Provides-Extra: scraper
Provides-Extra: app
Provides-Extra: all
License-File: LICENSE
